[
  {
    "epoch": 1,
    "global_step": 200,
    "train_loss": 0.7505467082560062,
    "train_miou": 0.5869583487510681,
    "val_loss": 0.6230507381443907,
    "val_miou": 0.6524426937103271,
    "lr": 3.9999999999999996e-05,
    "lr_dict": {
      "encoder_decay": 3.9999999999999996e-05,
      "encoder_no_decay": 3.9999999999999996e-05,
      "head_decay": 0.0004,
      "head_no_decay": 0.0004
    },
    "best_miou": 0.6524426937103271,
    "is_best": true,
    "early_bad_epochs": 0,
    "lr_encoder_decay": 3.9999999999999996e-05,
    "lr_encoder_no_decay": 3.9999999999999996e-05,
    "lr_head_decay": 0.0004,
    "lr_head_no_decay": 0.0004
  },
  {
    "epoch": 2,
    "global_step": 400,
    "train_loss": 0.5660482521355152,
    "train_miou": 0.6594656705856323,
    "val_loss": 0.5568183108503595,
    "val_miou": 0.6726616024971008,
    "lr": 6e-05,
    "lr_dict": {
      "encoder_decay": 6e-05,
      "encoder_no_decay": 6e-05,
      "head_decay": 0.0006000000000000001,
      "head_no_decay": 0.0006000000000000001
    },
    "best_miou": 0.6726616024971008,
    "is_best": true,
    "early_bad_epochs": 0,
    "lr_encoder_decay": 6e-05,
    "lr_encoder_no_decay": 6e-05,
    "lr_head_decay": 0.0006000000000000001,
    "lr_head_no_decay": 0.0006000000000000001
  },
  {
    "epoch": 3,
    "global_step": 600,
    "train_loss": 0.5062075993418693,
    "train_miou": 0.6891605257987976,
    "val_loss": 0.5381157565586673,
    "val_miou": 0.6758459210395813,
    "lr": 6e-05,
    "lr_dict": {
      "encoder_decay": 6e-05,
      "encoder_no_decay": 6e-05,
      "head_decay": 0.0006000000000000001,
      "head_no_decay": 0.0006000000000000001
    },
    "best_miou": 0.6758459210395813,
    "is_best": true,
    "early_bad_epochs": 0,
    "lr_encoder_decay": 6e-05,
    "lr_encoder_no_decay": 6e-05,
    "lr_head_decay": 0.0006000000000000001,
    "lr_head_no_decay": 0.0006000000000000001
  },
  {
    "epoch": 4,
    "global_step": 800,
    "train_loss": 0.4534758749604225,
    "train_miou": 0.7226402759552002,
    "val_loss": 0.525830499350731,
    "val_miou": 0.6870753765106201,
    "lr": 5.938144329896908e-05,
    "lr_dict": {
      "encoder_decay": 5.938144329896908e-05,
      "encoder_no_decay": 5.938144329896908e-05,
      "head_decay": 0.0005938144329896908,
      "head_no_decay": 0.0005938144329896908
    },
    "best_miou": 0.6870753765106201,
    "is_best": true,
    "early_bad_epochs": 0,
    "lr_encoder_decay": 5.938144329896908e-05,
    "lr_encoder_no_decay": 5.938144329896908e-05,
    "lr_head_decay": 0.0005938144329896908,
    "lr_head_no_decay": 0.0005938144329896908
  },
  {
    "epoch": 5,
    "global_step": 1000,
    "train_loss": 0.4192097809910774,
    "train_miou": 0.7445207834243774,
    "val_loss": 0.5369580123812107,
    "val_miou": 0.6966385841369629,
    "lr": 5.876288659793814e-05,
    "lr_dict": {
      "encoder_decay": 5.876288659793814e-05,
      "encoder_no_decay": 5.876288659793814e-05,
      "head_decay": 0.0005876288659793815,
      "head_no_decay": 0.0005876288659793815
    },
    "best_miou": 0.6966385841369629,
    "is_best": true,
    "early_bad_epochs": 0,
    "lr_encoder_decay": 5.876288659793814e-05,
    "lr_encoder_no_decay": 5.876288659793814e-05,
    "lr_head_decay": 0.0005876288659793815,
    "lr_head_no_decay": 0.0005876288659793815
  },
  {
    "epoch": 6,
    "global_step": 1200,
    "train_loss": 0.3964677350223064,
    "train_miou": 0.754980206489563,
    "val_loss": 0.5261613447677913,
    "val_miou": 0.6901964545249939,
    "lr": 5.814432989690722e-05,
    "lr_dict": {
      "encoder_decay": 5.814432989690722e-05,
      "encoder_no_decay": 5.814432989690722e-05,
      "head_decay": 0.0005814432989690722,
      "head_no_decay": 0.0005814432989690722
    },
    "best_miou": 0.6966385841369629,
    "is_best": false,
    "early_bad_epochs": 1,
    "lr_encoder_decay": 5.814432989690722e-05,
    "lr_encoder_no_decay": 5.814432989690722e-05,
    "lr_head_decay": 0.0005814432989690722,
    "lr_head_no_decay": 0.0005814432989690722
  },
  {
    "epoch": 7,
    "global_step": 1400,
    "train_loss": 0.37919710621237757,
    "train_miou": 0.7639122009277344,
    "val_loss": 0.5202067012857334,
    "val_miou": 0.7025459408760071,
    "lr": 5.752577319587629e-05,
    "lr_dict": {
      "encoder_decay": 5.752577319587629e-05,
      "encoder_no_decay": 5.752577319587629e-05,
      "head_decay": 0.0005752577319587629,
      "head_no_decay": 0.0005752577319587629
    },
    "best_miou": 0.7025459408760071,
    "is_best": true,
    "early_bad_epochs": 0,
    "lr_encoder_decay": 5.752577319587629e-05,
    "lr_encoder_no_decay": 5.752577319587629e-05,
    "lr_head_decay": 0.0005752577319587629,
    "lr_head_no_decay": 0.0005752577319587629
  },
  {
    "epoch": 8,
    "global_step": 1600,
    "train_loss": 0.3524822290241718,
    "train_miou": 0.7817606925964355,
    "val_loss": 0.5147904297107546,
    "val_miou": 0.7053860425949097,
    "lr": 5.690721649484536e-05,
    "lr_dict": {
      "encoder_decay": 5.690721649484536e-05,
      "encoder_no_decay": 5.690721649484536e-05,
      "head_decay": 0.0005690721649484537,
      "head_no_decay": 0.0005690721649484537
    },
    "best_miou": 0.7053860425949097,
    "is_best": true,
    "early_bad_epochs": 0,
    "lr_encoder_decay": 5.690721649484536e-05,
    "lr_encoder_no_decay": 5.690721649484536e-05,
    "lr_head_decay": 0.0005690721649484537,
    "lr_head_no_decay": 0.0005690721649484537
  },
  {
    "epoch": 9,
    "global_step": 1800,
    "train_loss": 0.33654636293649676,
    "train_miou": 0.7885732054710388,
    "val_loss": 0.519664083355166,
    "val_miou": 0.7045934796333313,
    "lr": 5.628865979381443e-05,
    "lr_dict": {
      "encoder_decay": 5.628865979381443e-05,
      "encoder_no_decay": 5.628865979381443e-05,
      "head_decay": 0.0005628865979381444,
      "head_no_decay": 0.0005628865979381444
    },
    "best_miou": 0.7053860425949097,
    "is_best": false,
    "early_bad_epochs": 1,
    "lr_encoder_decay": 5.628865979381443e-05,
    "lr_encoder_no_decay": 5.628865979381443e-05,
    "lr_head_decay": 0.0005628865979381444,
    "lr_head_no_decay": 0.0005628865979381444
  },
  {
    "epoch": 10,
    "global_step": 2000,
    "train_loss": 0.3297116796672344,
    "train_miou": 0.7943452596664429,
    "val_loss": 0.5277127617685665,
    "val_miou": 0.709479808807373,
    "lr": 5.567010309278351e-05,
    "lr_dict": {
      "encoder_decay": 5.567010309278351e-05,
      "encoder_no_decay": 5.567010309278351e-05,
      "head_decay": 0.0005567010309278351,
      "head_no_decay": 0.0005567010309278351
    },
    "best_miou": 0.709479808807373,
    "is_best": true,
    "early_bad_epochs": 0,
    "lr_encoder_decay": 5.567010309278351e-05,
    "lr_encoder_no_decay": 5.567010309278351e-05,
    "lr_head_decay": 0.0005567010309278351,
    "lr_head_no_decay": 0.0005567010309278351
  },
  {
    "epoch": 11,
    "global_step": 2200,
    "train_loss": 0.31940982192754747,
    "train_miou": 0.7987767457962036,
    "val_loss": 0.5212211975910394,
    "val_miou": 0.7159969210624695,
    "lr": 5.5051546391752574e-05,
    "lr_dict": {
      "encoder_decay": 5.5051546391752574e-05,
      "encoder_no_decay": 5.5051546391752574e-05,
      "head_decay": 0.0005505154639175258,
      "head_no_decay": 0.0005505154639175258
    },
    "best_miou": 0.7159969210624695,
    "is_best": true,
    "early_bad_epochs": 0,
    "lr_encoder_decay": 5.5051546391752574e-05,
    "lr_encoder_no_decay": 5.5051546391752574e-05,
    "lr_head_decay": 0.0005505154639175258,
    "lr_head_no_decay": 0.0005505154639175258
  },
  {
    "epoch": 12,
    "global_step": 2400,
    "train_loss": 0.30745480783283713,
    "train_miou": 0.8074597716331482,
    "val_loss": 0.5219814805268067,
    "val_miou": 0.7131068110466003,
    "lr": 5.443298969072165e-05,
    "lr_dict": {
      "encoder_decay": 5.443298969072165e-05,
      "encoder_no_decay": 5.443298969072165e-05,
      "head_decay": 0.0005443298969072165,
      "head_no_decay": 0.0005443298969072165
    },
    "best_miou": 0.7159969210624695,
    "is_best": false,
    "early_bad_epochs": 1,
    "lr_encoder_decay": 5.443298969072165e-05,
    "lr_encoder_no_decay": 5.443298969072165e-05,
    "lr_head_decay": 0.0005443298969072165,
    "lr_head_no_decay": 0.0005443298969072165
  },
  {
    "epoch": 13,
    "global_step": 2600,
    "train_loss": 0.2967692010104656,
    "train_miou": 0.8104217052459717,
    "val_loss": 0.5478679411516988,
    "val_miou": 0.7102207541465759,
    "lr": 5.381443298969072e-05,
    "lr_dict": {
      "encoder_decay": 5.381443298969072e-05,
      "encoder_no_decay": 5.381443298969072e-05,
      "head_decay": 0.0005381443298969073,
      "head_no_decay": 0.0005381443298969073
    },
    "best_miou": 0.7159969210624695,
    "is_best": false,
    "early_bad_epochs": 2,
    "lr_encoder_decay": 5.381443298969072e-05,
    "lr_encoder_no_decay": 5.381443298969072e-05,
    "lr_head_decay": 0.0005381443298969073,
    "lr_head_no_decay": 0.0005381443298969073
  },
  {
    "epoch": 14,
    "global_step": 2800,
    "train_loss": 0.28904072776436807,
    "train_miou": 0.8171054720878601,
    "val_loss": 0.5437243930224714,
    "val_miou": 0.7056676745414734,
    "lr": 5.319587628865979e-05,
    "lr_dict": {
      "encoder_decay": 5.319587628865979e-05,
      "encoder_no_decay": 5.319587628865979e-05,
      "head_decay": 0.000531958762886598,
      "head_no_decay": 0.000531958762886598
    },
    "best_miou": 0.7159969210624695,
    "is_best": false,
    "early_bad_epochs": 3,
    "lr_encoder_decay": 5.319587628865979e-05,
    "lr_encoder_no_decay": 5.319587628865979e-05,
    "lr_head_decay": 0.000531958762886598,
    "lr_head_no_decay": 0.000531958762886598
  },
  {
    "epoch": 15,
    "global_step": 3000,
    "train_loss": 0.28527282789349556,
    "train_miou": 0.818749725818634,
    "val_loss": 0.5210451333980842,
    "val_miou": 0.7162477374076843,
    "lr": 5.2577319587628864e-05,
    "lr_dict": {
      "encoder_decay": 5.2577319587628864e-05,
      "encoder_no_decay": 5.2577319587628864e-05,
      "head_decay": 0.0005257731958762887,
      "head_no_decay": 0.0005257731958762887
    },
    "best_miou": 0.7162477374076843,
    "is_best": true,
    "early_bad_epochs": 0,
    "lr_encoder_decay": 5.2577319587628864e-05,
    "lr_encoder_no_decay": 5.2577319587628864e-05,
    "lr_head_decay": 0.0005257731958762887,
    "lr_head_no_decay": 0.0005257731958762887
  },
  {
    "epoch": 16,
    "global_step": 3200,
    "train_loss": 0.2747668282687664,
    "train_miou": 0.8239888548851013,
    "val_loss": 0.5334960002030058,
    "val_miou": 0.7161603569984436,
    "lr": 5.195876288659794e-05,
    "lr_dict": {
      "encoder_decay": 5.195876288659794e-05,
      "encoder_no_decay": 5.195876288659794e-05,
      "head_decay": 0.0005195876288659794,
      "head_no_decay": 0.0005195876288659794
    },
    "best_miou": 0.7162477374076843,
    "is_best": false,
    "early_bad_epochs": 1,
    "lr_encoder_decay": 5.195876288659794e-05,
    "lr_encoder_no_decay": 5.195876288659794e-05,
    "lr_head_decay": 0.0005195876288659794,
    "lr_head_no_decay": 0.0005195876288659794
  },
  {
    "epoch": 17,
    "global_step": 3400,
    "train_loss": 0.2738951087743044,
    "train_miou": 0.8264335989952087,
    "val_loss": 0.5293473160912838,
    "val_miou": 0.7169281840324402,
    "lr": 5.134020618556701e-05,
    "lr_dict": {
      "encoder_decay": 5.134020618556701e-05,
      "encoder_no_decay": 5.134020618556701e-05,
      "head_decay": 0.0005134020618556702,
      "head_no_decay": 0.0005134020618556702
    },
    "best_miou": 0.7169281840324402,
    "is_best": true,
    "early_bad_epochs": 0,
    "lr_encoder_decay": 5.134020618556701e-05,
    "lr_encoder_no_decay": 5.134020618556701e-05,
    "lr_head_decay": 0.0005134020618556702,
    "lr_head_no_decay": 0.0005134020618556702
  },
  {
    "epoch": 18,
    "global_step": 3600,
    "train_loss": 0.26192635610699655,
    "train_miou": 0.8294181823730469,
    "val_loss": 0.5332873610440146,
    "val_miou": 0.7163546681404114,
    "lr": 5.072164948453608e-05,
    "lr_dict": {
      "encoder_decay": 5.072164948453608e-05,
      "encoder_no_decay": 5.072164948453608e-05,
      "head_decay": 0.0005072164948453609,
      "head_no_decay": 0.0005072164948453609
    },
    "best_miou": 0.7169281840324402,
    "is_best": false,
    "early_bad_epochs": 1,
    "lr_encoder_decay": 5.072164948453608e-05,
    "lr_encoder_no_decay": 5.072164948453608e-05,
    "lr_head_decay": 0.0005072164948453609,
    "lr_head_no_decay": 0.0005072164948453609
  },
  {
    "epoch": 19,
    "global_step": 3800,
    "train_loss": 0.2588958679139614,
    "train_miou": 0.833293616771698,
    "val_loss": 0.5395209360592471,
    "val_miou": 0.7175531983375549,
    "lr": 5.010309278350516e-05,
    "lr_dict": {
      "encoder_decay": 5.010309278350516e-05,
      "encoder_no_decay": 5.010309278350516e-05,
      "head_decay": 0.0005010309278350516,
      "head_no_decay": 0.0005010309278350516
    },
    "best_miou": 0.7175531983375549,
    "is_best": true,
    "early_bad_epochs": 0,
    "lr_encoder_decay": 5.010309278350516e-05,
    "lr_encoder_no_decay": 5.010309278350516e-05,
    "lr_head_decay": 0.0005010309278350516,
    "lr_head_no_decay": 0.0005010309278350516
  },
  {
    "epoch": 20,
    "global_step": 4000,
    "train_loss": 0.25089496485888957,
    "train_miou": 0.8361400961875916,
    "val_loss": 0.5383021487978291,
    "val_miou": 0.7203514575958252,
    "lr": 4.9484536082474225e-05,
    "lr_dict": {
      "encoder_decay": 4.9484536082474225e-05,
      "encoder_no_decay": 4.9484536082474225e-05,
      "head_decay": 0.0004948453608247423,
      "head_no_decay": 0.0004948453608247423
    },
    "best_miou": 0.7203514575958252,
    "is_best": true,
    "early_bad_epochs": 0,
    "lr_encoder_decay": 4.9484536082474225e-05,
    "lr_encoder_no_decay": 4.9484536082474225e-05,
    "lr_head_decay": 0.0004948453608247423,
    "lr_head_no_decay": 0.0004948453608247423
  },
  {
    "epoch": 21,
    "global_step": 4200,
    "train_loss": 0.24715526185929776,
    "train_miou": 0.8402316570281982,
    "val_loss": 0.5391846291830974,
    "val_miou": 0.717477023601532,
    "lr": 4.88659793814433e-05,
    "lr_dict": {
      "encoder_decay": 4.88659793814433e-05,
      "encoder_no_decay": 4.88659793814433e-05,
      "head_decay": 0.000488659793814433,
      "head_no_decay": 0.000488659793814433
    },
    "best_miou": 0.7203514575958252,
    "is_best": false,
    "early_bad_epochs": 1,
    "lr_encoder_decay": 4.88659793814433e-05,
    "lr_encoder_no_decay": 4.88659793814433e-05,
    "lr_head_decay": 0.000488659793814433,
    "lr_head_no_decay": 0.000488659793814433
  },
  {
    "epoch": 22,
    "global_step": 4400,
    "train_loss": 0.2470399283617735,
    "train_miou": 0.8364250063896179,
    "val_loss": 0.5357650409778351,
    "val_miou": 0.7155759930610657,
    "lr": 4.824742268041237e-05,
    "lr_dict": {
      "encoder_decay": 4.824742268041237e-05,
      "encoder_no_decay": 4.824742268041237e-05,
      "head_decay": 0.00048247422680412376,
      "head_no_decay": 0.00048247422680412376
    },
    "best_miou": 0.7203514575958252,
    "is_best": false,
    "early_bad_epochs": 2,
    "lr_encoder_decay": 4.824742268041237e-05,
    "lr_encoder_no_decay": 4.824742268041237e-05,
    "lr_head_decay": 0.00048247422680412376,
    "lr_head_no_decay": 0.00048247422680412376
  },
  {
    "epoch": 23,
    "global_step": 4600,
    "train_loss": 0.24264263831079005,
    "train_miou": 0.841363787651062,
    "val_loss": 0.5452010602199385,
    "val_miou": 0.7197033166885376,
    "lr": 4.762886597938145e-05,
    "lr_dict": {
      "encoder_decay": 4.762886597938145e-05,
      "encoder_no_decay": 4.762886597938145e-05,
      "head_decay": 0.00047628865979381453,
      "head_no_decay": 0.00047628865979381453
    },
    "best_miou": 0.7203514575958252,
    "is_best": false,
    "early_bad_epochs": 3,
    "lr_encoder_decay": 4.762886597938145e-05,
    "lr_encoder_no_decay": 4.762886597938145e-05,
    "lr_head_decay": 0.00047628865979381453,
    "lr_head_no_decay": 0.00047628865979381453
  },
  {
    "epoch": 24,
    "global_step": 4800,
    "train_loss": 0.23746350161731244,
    "train_miou": 0.8416041135787964,
    "val_loss": 0.5478615323311002,
    "val_miou": 0.7152467370033264,
    "lr": 4.7010309278350514e-05,
    "lr_dict": {
      "encoder_decay": 4.7010309278350514e-05,
      "encoder_no_decay": 4.7010309278350514e-05,
      "head_decay": 0.0004701030927835052,
      "head_no_decay": 0.0004701030927835052
    },
    "best_miou": 0.7203514575958252,
    "is_best": false,
    "early_bad_epochs": 4,
    "lr_encoder_decay": 4.7010309278350514e-05,
    "lr_encoder_no_decay": 4.7010309278350514e-05,
    "lr_head_decay": 0.0004701030927835052,
    "lr_head_no_decay": 0.0004701030927835052
  },
  {
    "epoch": 25,
    "global_step": 5000,
    "train_loss": 0.23017046086490153,
    "train_miou": 0.8478861451148987,
    "val_loss": 0.5435705176127955,
    "val_miou": 0.7199802398681641,
    "lr": 4.639175257731959e-05,
    "lr_dict": {
      "encoder_decay": 4.639175257731959e-05,
      "encoder_no_decay": 4.639175257731959e-05,
      "head_decay": 0.0004639175257731959,
      "head_no_decay": 0.0004639175257731959
    },
    "best_miou": 0.7203514575958252,
    "is_best": false,
    "early_bad_epochs": 5,
    "lr_encoder_decay": 4.639175257731959e-05,
    "lr_encoder_no_decay": 4.639175257731959e-05,
    "lr_head_decay": 0.0004639175257731959,
    "lr_head_no_decay": 0.0004639175257731959
  },
  {
    "epoch": 26,
    "global_step": 5200,
    "train_loss": 0.22877986937761308,
    "train_miou": 0.848980724811554,
    "val_loss": 0.5509344066305114,
    "val_miou": 0.7210182547569275,
    "lr": 4.5773195876288656e-05,
    "lr_dict": {
      "encoder_decay": 4.5773195876288656e-05,
      "encoder_no_decay": 4.5773195876288656e-05,
      "head_decay": 0.0004577319587628866,
      "head_no_decay": 0.0004577319587628866
    },
    "best_miou": 0.7210182547569275,
    "is_best": true,
    "early_bad_epochs": 0,
    "lr_encoder_decay": 4.5773195876288656e-05,
    "lr_encoder_no_decay": 4.5773195876288656e-05,
    "lr_head_decay": 0.0004577319587628866,
    "lr_head_no_decay": 0.0004577319587628866
  },
  {
    "epoch": 27,
    "global_step": 5400,
    "train_loss": 0.2235343759506941,
    "train_miou": 0.8519788980484009,
    "val_loss": 0.5539418241660583,
    "val_miou": 0.7200406789779663,
    "lr": 4.5154639175257733e-05,
    "lr_dict": {
      "encoder_decay": 4.5154639175257733e-05,
      "encoder_no_decay": 4.5154639175257733e-05,
      "head_decay": 0.00045154639175257736,
      "head_no_decay": 0.00045154639175257736
    },
    "best_miou": 0.7210182547569275,
    "is_best": false,
    "early_bad_epochs": 1,
    "lr_encoder_decay": 4.5154639175257733e-05,
    "lr_encoder_no_decay": 4.5154639175257733e-05,
    "lr_head_decay": 0.00045154639175257736,
    "lr_head_no_decay": 0.00045154639175257736
  },
  {
    "epoch": 28,
    "global_step": 5600,
    "train_loss": 0.21886802278459072,
    "train_miou": 0.8539220690727234,
    "val_loss": 0.5603687754405543,
    "val_miou": 0.7178633213043213,
    "lr": 4.4536082474226804e-05,
    "lr_dict": {
      "encoder_decay": 4.4536082474226804e-05,
      "encoder_no_decay": 4.4536082474226804e-05,
      "head_decay": 0.0004453608247422681,
      "head_no_decay": 0.0004453608247422681
    },
    "best_miou": 0.7210182547569275,
    "is_best": false,
    "early_bad_epochs": 2,
    "lr_encoder_decay": 4.4536082474226804e-05,
    "lr_encoder_no_decay": 4.4536082474226804e-05,
    "lr_head_decay": 0.0004453608247422681,
    "lr_head_no_decay": 0.0004453608247422681
  },
  {
    "epoch": 29,
    "global_step": 5800,
    "train_loss": 0.2225428081303835,
    "train_miou": 0.8535634279251099,
    "val_loss": 0.5470711910372297,
    "val_miou": 0.7228713035583496,
    "lr": 4.391752577319588e-05,
    "lr_dict": {
      "encoder_decay": 4.391752577319588e-05,
      "encoder_no_decay": 4.391752577319588e-05,
      "head_decay": 0.00043917525773195886,
      "head_no_decay": 0.00043917525773195886
    },
    "best_miou": 0.7228713035583496,
    "is_best": true,
    "early_bad_epochs": 0,
    "lr_encoder_decay": 4.391752577319588e-05,
    "lr_encoder_no_decay": 4.391752577319588e-05,
    "lr_head_decay": 0.00043917525773195886,
    "lr_head_no_decay": 0.00043917525773195886
  },
  {
    "epoch": 30,
    "global_step": 6000,
    "train_loss": 0.2150559164583683,
    "train_miou": 0.8575587868690491,
    "val_loss": 0.548088918325349,
    "val_miou": 0.7196292877197266,
    "lr": 4.3298969072164946e-05,
    "lr_dict": {
      "encoder_decay": 4.3298969072164946e-05,
      "encoder_no_decay": 4.3298969072164946e-05,
      "head_decay": 0.0004329896907216495,
      "head_no_decay": 0.0004329896907216495
    },
    "best_miou": 0.7228713035583496,
    "is_best": false,
    "early_bad_epochs": 1,
    "lr_encoder_decay": 4.3298969072164946e-05,
    "lr_encoder_no_decay": 4.3298969072164946e-05,
    "lr_head_decay": 0.0004329896907216495,
    "lr_head_no_decay": 0.0004329896907216495
  },
  {
    "epoch": 31,
    "global_step": 6200,
    "train_loss": 0.21496414922177792,
    "train_miou": 0.8563486337661743,
    "val_loss": 0.5568874296296407,
    "val_miou": 0.7209385633468628,
    "lr": 4.268041237113402e-05,
    "lr_dict": {
      "encoder_decay": 4.268041237113402e-05,
      "encoder_no_decay": 4.268041237113402e-05,
      "head_decay": 0.00042680412371134025,
      "head_no_decay": 0.00042680412371134025
    },
    "best_miou": 0.7228713035583496,
    "is_best": false,
    "early_bad_epochs": 2,
    "lr_encoder_decay": 4.268041237113402e-05,
    "lr_encoder_no_decay": 4.268041237113402e-05,
    "lr_head_decay": 0.00042680412371134025,
    "lr_head_no_decay": 0.00042680412371134025
  },
  {
    "epoch": 32,
    "global_step": 6400,
    "train_loss": 0.21147822879254818,
    "train_miou": 0.8580165505409241,
    "val_loss": 0.5538589716544879,
    "val_miou": 0.7234550714492798,
    "lr": 4.2061855670103094e-05,
    "lr_dict": {
      "encoder_decay": 4.2061855670103094e-05,
      "encoder_no_decay": 4.2061855670103094e-05,
      "head_decay": 0.0004206185567010309,
      "head_no_decay": 0.0004206185567010309
    },
    "best_miou": 0.7234550714492798,
    "is_best": true,
    "early_bad_epochs": 0,
    "lr_encoder_decay": 4.2061855670103094e-05,
    "lr_encoder_no_decay": 4.2061855670103094e-05,
    "lr_head_decay": 0.0004206185567010309,
    "lr_head_no_decay": 0.0004206185567010309
  },
  {
    "epoch": 33,
    "global_step": 6600,
    "train_loss": 0.21147060476243495,
    "train_miou": 0.8584091663360596,
    "val_loss": 0.5558589732118429,
    "val_miou": 0.7240817546844482,
    "lr": 4.1443298969072165e-05,
    "lr_dict": {
      "encoder_decay": 4.1443298969072165e-05,
      "encoder_no_decay": 4.1443298969072165e-05,
      "head_decay": 0.0004144329896907217,
      "head_no_decay": 0.0004144329896907217
    },
    "best_miou": 0.7240817546844482,
    "is_best": true,
    "early_bad_epochs": 0,
    "lr_encoder_decay": 4.1443298969072165e-05,
    "lr_encoder_no_decay": 4.1443298969072165e-05,
    "lr_head_decay": 0.0004144329896907217,
    "lr_head_no_decay": 0.0004144329896907217
  },
  {
    "epoch": 34,
    "global_step": 6800,
    "train_loss": 0.20688105978071689,
    "train_miou": 0.8621522784233093,
    "val_loss": 0.5543759293450511,
    "val_miou": 0.7262190580368042,
    "lr": 4.082474226804124e-05,
    "lr_dict": {
      "encoder_decay": 4.082474226804124e-05,
      "encoder_no_decay": 4.082474226804124e-05,
      "head_decay": 0.0004082474226804124,
      "head_no_decay": 0.0004082474226804124
    },
    "best_miou": 0.7262190580368042,
    "is_best": true,
    "early_bad_epochs": 0,
    "lr_encoder_decay": 4.082474226804124e-05,
    "lr_encoder_no_decay": 4.082474226804124e-05,
    "lr_head_decay": 0.0004082474226804124,
    "lr_head_no_decay": 0.0004082474226804124
  },
  {
    "epoch": 35,
    "global_step": 7000,
    "train_loss": 0.2046384710818529,
    "train_miou": 0.8627645373344421,
    "val_loss": 0.563509659226892,
    "val_miou": 0.7240064740180969,
    "lr": 4.020618556701031e-05,
    "lr_dict": {
      "encoder_decay": 4.020618556701031e-05,
      "encoder_no_decay": 4.020618556701031e-05,
      "head_decay": 0.0004020618556701032,
      "head_no_decay": 0.0004020618556701032
    },
    "best_miou": 0.7262190580368042,
    "is_best": false,
    "early_bad_epochs": 1,
    "lr_encoder_decay": 4.020618556701031e-05,
    "lr_encoder_no_decay": 4.020618556701031e-05,
    "lr_head_decay": 0.0004020618556701032,
    "lr_head_no_decay": 0.0004020618556701032
  },
  {
    "epoch": 36,
    "global_step": 7200,
    "train_loss": 0.19986749306321144,
    "train_miou": 0.8644423484802246,
    "val_loss": 0.5707858994676562,
    "val_miou": 0.7208200097084045,
    "lr": 3.9587628865979384e-05,
    "lr_dict": {
      "encoder_decay": 3.9587628865979384e-05,
      "encoder_no_decay": 3.9587628865979384e-05,
      "head_decay": 0.00039587628865979385,
      "head_no_decay": 0.00039587628865979385
    },
    "best_miou": 0.7262190580368042,
    "is_best": false,
    "early_bad_epochs": 2,
    "lr_encoder_decay": 3.9587628865979384e-05,
    "lr_encoder_no_decay": 3.9587628865979384e-05,
    "lr_head_decay": 0.00039587628865979385,
    "lr_head_no_decay": 0.00039587628865979385
  },
  {
    "epoch": 37,
    "global_step": 7400,
    "train_loss": 0.20034850910305976,
    "train_miou": 0.8644997477531433,
    "val_loss": 0.5549013224141351,
    "val_miou": 0.7265368103981018,
    "lr": 3.8969072164948455e-05,
    "lr_dict": {
      "encoder_decay": 3.8969072164948455e-05,
      "encoder_no_decay": 3.8969072164948455e-05,
      "head_decay": 0.00038969072164948457,
      "head_no_decay": 0.00038969072164948457
    },
    "best_miou": 0.7265368103981018,
    "is_best": true,
    "early_bad_epochs": 0,
    "lr_encoder_decay": 3.8969072164948455e-05,
    "lr_encoder_no_decay": 3.8969072164948455e-05,
    "lr_head_decay": 0.00038969072164948457,
    "lr_head_no_decay": 0.00038969072164948457
  },
  {
    "epoch": 38,
    "global_step": 7600,
    "train_loss": 0.196822067797184,
    "train_miou": 0.8665536642074585,
    "val_loss": 0.567439217725998,
    "val_miou": 0.7211078405380249,
    "lr": 3.8350515463917525e-05,
    "lr_dict": {
      "encoder_decay": 3.8350515463917525e-05,
      "encoder_no_decay": 3.8350515463917525e-05,
      "head_decay": 0.00038350515463917524,
      "head_no_decay": 0.00038350515463917524
    },
    "best_miou": 0.7265368103981018,
    "is_best": false,
    "early_bad_epochs": 1,
    "lr_encoder_decay": 3.8350515463917525e-05,
    "lr_encoder_no_decay": 3.8350515463917525e-05,
    "lr_head_decay": 0.00038350515463917524,
    "lr_head_no_decay": 0.00038350515463917524
  },
  {
    "epoch": 39,
    "global_step": 7800,
    "train_loss": 0.19683250851929188,
    "train_miou": 0.8671453595161438,
    "val_loss": 0.6365155022719811,
    "val_miou": 0.7185485363006592,
    "lr": 3.7731958762886596e-05,
    "lr_dict": {
      "encoder_decay": 3.7731958762886596e-05,
      "encoder_no_decay": 3.7731958762886596e-05,
      "head_decay": 0.000377319587628866,
      "head_no_decay": 0.000377319587628866
    },
    "best_miou": 0.7265368103981018,
    "is_best": false,
    "early_bad_epochs": 2,
    "lr_encoder_decay": 3.7731958762886596e-05,
    "lr_encoder_no_decay": 3.7731958762886596e-05,
    "lr_head_decay": 0.000377319587628866,
    "lr_head_no_decay": 0.000377319587628866
  },
  {
    "epoch": 40,
    "global_step": 8000,
    "train_loss": 0.19432969011366366,
    "train_miou": 0.8698354959487915,
    "val_loss": 0.5772335611540695,
    "val_miou": 0.7216236591339111,
    "lr": 3.7113402061855674e-05,
    "lr_dict": {
      "encoder_decay": 3.7113402061855674e-05,
      "encoder_no_decay": 3.7113402061855674e-05,
      "head_decay": 0.00037113402061855674,
      "head_no_decay": 0.00037113402061855674
    },
    "best_miou": 0.7265368103981018,
    "is_best": false,
    "early_bad_epochs": 3,
    "lr_encoder_decay": 3.7113402061855674e-05,
    "lr_encoder_no_decay": 3.7113402061855674e-05,
    "lr_head_decay": 0.00037113402061855674,
    "lr_head_no_decay": 0.00037113402061855674
  },
  {
    "epoch": 41,
    "global_step": 8200,
    "train_loss": 0.1921880676969886,
    "train_miou": 0.8712451457977295,
    "val_loss": 0.5688198343873612,
    "val_miou": 0.7205562591552734,
    "lr": 3.6494845360824744e-05,
    "lr_dict": {
      "encoder_decay": 3.6494845360824744e-05,
      "encoder_no_decay": 3.6494845360824744e-05,
      "head_decay": 0.0003649484536082475,
      "head_no_decay": 0.0003649484536082475
    },
    "best_miou": 0.7265368103981018,
    "is_best": false,
    "early_bad_epochs": 4,
    "lr_encoder_decay": 3.6494845360824744e-05,
    "lr_encoder_no_decay": 3.6494845360824744e-05,
    "lr_head_decay": 0.0003649484536082475,
    "lr_head_no_decay": 0.0003649484536082475
  },
  {
    "epoch": 42,
    "global_step": 8400,
    "train_loss": 0.19063531227409838,
    "train_miou": 0.8701952695846558,
    "val_loss": 0.5722590651124569,
    "val_miou": 0.724877119064331,
    "lr": 3.5876288659793815e-05,
    "lr_dict": {
      "encoder_decay": 3.5876288659793815e-05,
      "encoder_no_decay": 3.5876288659793815e-05,
      "head_decay": 0.0003587628865979382,
      "head_no_decay": 0.0003587628865979382
    },
    "best_miou": 0.7265368103981018,
    "is_best": false,
    "early_bad_epochs": 5,
    "lr_encoder_decay": 3.5876288659793815e-05,
    "lr_encoder_no_decay": 3.5876288659793815e-05,
    "lr_head_decay": 0.0003587628865979382,
    "lr_head_no_decay": 0.0003587628865979382
  },
  {
    "epoch": 43,
    "global_step": 8600,
    "train_loss": 0.1869362211972475,
    "train_miou": 0.871981143951416,
    "val_loss": 0.5767774984167127,
    "val_miou": 0.7225053906440735,
    "lr": 3.5257731958762886e-05,
    "lr_dict": {
      "encoder_decay": 3.5257731958762886e-05,
      "encoder_no_decay": 3.5257731958762886e-05,
      "head_decay": 0.0003525773195876289,
      "head_no_decay": 0.0003525773195876289
    },
    "best_miou": 0.7265368103981018,
    "is_best": false,
    "early_bad_epochs": 6,
    "lr_encoder_decay": 3.5257731958762886e-05,
    "lr_encoder_no_decay": 3.5257731958762886e-05,
    "lr_head_decay": 0.0003525773195876289,
    "lr_head_no_decay": 0.0003525773195876289
  },
  {
    "epoch": 44,
    "global_step": 8800,
    "train_loss": 0.1858269155025482,
    "train_miou": 0.873916745185852,
    "val_loss": 0.5759777485443454,
    "val_miou": 0.7255421876907349,
    "lr": 3.4639175257731957e-05,
    "lr_dict": {
      "encoder_decay": 3.4639175257731957e-05,
      "encoder_no_decay": 3.4639175257731957e-05,
      "head_decay": 0.00034639175257731957,
      "head_no_decay": 0.00034639175257731957
    },
    "best_miou": 0.7265368103981018,
    "is_best": false,
    "early_bad_epochs": 7,
    "lr_encoder_decay": 3.4639175257731957e-05,
    "lr_encoder_no_decay": 3.4639175257731957e-05,
    "lr_head_decay": 0.00034639175257731957,
    "lr_head_no_decay": 0.00034639175257731957
  },
  {
    "epoch": 45,
    "global_step": 9000,
    "train_loss": 0.18903492864221336,
    "train_miou": 0.8725600838661194,
    "val_loss": 0.5836397861612255,
    "val_miou": 0.7213754057884216,
    "lr": 3.4020618556701034e-05,
    "lr_dict": {
      "encoder_decay": 3.4020618556701034e-05,
      "encoder_no_decay": 3.4020618556701034e-05,
      "head_decay": 0.00034020618556701034,
      "head_no_decay": 0.00034020618556701034
    },
    "best_miou": 0.7265368103981018,
    "is_best": false,
    "early_bad_epochs": 8,
    "lr_encoder_decay": 3.4020618556701034e-05,
    "lr_encoder_no_decay": 3.4020618556701034e-05,
    "lr_head_decay": 0.00034020618556701034,
    "lr_head_no_decay": 0.00034020618556701034
  },
  {
    "epoch": 46,
    "global_step": 9200,
    "train_loss": 0.1814422545954585,
    "train_miou": 0.8749899864196777,
    "val_loss": 0.5814536577962303,
    "val_miou": 0.7249512076377869,
    "lr": 3.3402061855670105e-05,
    "lr_dict": {
      "encoder_decay": 3.3402061855670105e-05,
      "encoder_no_decay": 3.3402061855670105e-05,
      "head_decay": 0.00033402061855670106,
      "head_no_decay": 0.00033402061855670106
    },
    "best_miou": 0.7265368103981018,
    "is_best": false,
    "early_bad_epochs": 9,
    "lr_encoder_decay": 3.3402061855670105e-05,
    "lr_encoder_no_decay": 3.3402061855670105e-05,
    "lr_head_decay": 0.00033402061855670106,
    "lr_head_no_decay": 0.00033402061855670106
  },
  {
    "epoch": 47,
    "global_step": 9400,
    "train_loss": 0.17826566632837057,
    "train_miou": 0.8765106201171875,
    "val_loss": 0.5917530507583336,
    "val_miou": 0.7235451340675354,
    "lr": 3.278350515463918e-05,
    "lr_dict": {
      "encoder_decay": 3.278350515463918e-05,
      "encoder_no_decay": 3.278350515463918e-05,
      "head_decay": 0.00032783505154639184,
      "head_no_decay": 0.00032783505154639184
    },
    "best_miou": 0.7265368103981018,
    "is_best": false,
    "early_bad_epochs": 10,
    "lr_encoder_decay": 3.278350515463918e-05,
    "lr_encoder_no_decay": 3.278350515463918e-05,
    "lr_head_decay": 0.00032783505154639184,
    "lr_head_no_decay": 0.00032783505154639184
  },
  {
    "epoch": 48,
    "global_step": 9600,
    "train_loss": 0.17893683828413487,
    "train_miou": 0.8779540657997131,
    "val_loss": 0.5860847883623809,
    "val_miou": 0.7268238067626953,
    "lr": 3.2164948453608246e-05,
    "lr_dict": {
      "encoder_decay": 3.2164948453608246e-05,
      "encoder_no_decay": 3.2164948453608246e-05,
      "head_decay": 0.0003216494845360825,
      "head_no_decay": 0.0003216494845360825
    },
    "best_miou": 0.7268238067626953,
    "is_best": true,
    "early_bad_epochs": 0,
    "lr_encoder_decay": 3.2164948453608246e-05,
    "lr_encoder_no_decay": 3.2164948453608246e-05,
    "lr_head_decay": 0.0003216494845360825,
    "lr_head_no_decay": 0.0003216494845360825
  },
  {
    "epoch": 49,
    "global_step": 9800,
    "train_loss": 0.18100689973682166,
    "train_miou": 0.8748987317085266,
    "val_loss": 0.5855749623822462,
    "val_miou": 0.7276410460472107,
    "lr": 3.1546391752577324e-05,
    "lr_dict": {
      "encoder_decay": 3.1546391752577324e-05,
      "encoder_no_decay": 3.1546391752577324e-05,
      "head_decay": 0.0003154639175257732,
      "head_no_decay": 0.0003154639175257732
    },
    "best_miou": 0.7276410460472107,
    "is_best": true,
    "early_bad_epochs": 0,
    "lr_encoder_decay": 3.1546391752577324e-05,
    "lr_encoder_no_decay": 3.1546391752577324e-05,
    "lr_head_decay": 0.0003154639175257732,
    "lr_head_no_decay": 0.0003154639175257732
  },
  {
    "epoch": 50,
    "global_step": 10000,
    "train_loss": 0.17563413958996535,
    "train_miou": 0.8783095479011536,
    "val_loss": 0.5837961555701758,
    "val_miou": 0.7280662059783936,
    "lr": 3.092783505154639e-05,
    "lr_dict": {
      "encoder_decay": 3.092783505154639e-05,
      "encoder_no_decay": 3.092783505154639e-05,
      "head_decay": 0.0003092783505154639,
      "head_no_decay": 0.0003092783505154639
    },
    "best_miou": 0.7280662059783936,
    "is_best": true,
    "early_bad_epochs": 0,
    "lr_encoder_decay": 3.092783505154639e-05,
    "lr_encoder_no_decay": 3.092783505154639e-05,
    "lr_head_decay": 0.0003092783505154639,
    "lr_head_no_decay": 0.0003092783505154639
  },
  {
    "epoch": 51,
    "global_step": 10200,
    "train_loss": 0.1730859311297536,
    "train_miou": 0.8780501484870911,
    "val_loss": 0.5864430818651697,
    "val_miou": 0.7267193794250488,
    "lr": 3.0309278350515462e-05,
    "lr_dict": {
      "encoder_decay": 3.0309278350515462e-05,
      "encoder_no_decay": 3.0309278350515462e-05,
      "head_decay": 0.00030309278350515467,
      "head_no_decay": 0.00030309278350515467
    },
    "best_miou": 0.7280662059783936,
    "is_best": false,
    "early_bad_epochs": 1,
    "lr_encoder_decay": 3.0309278350515462e-05,
    "lr_encoder_no_decay": 3.0309278350515462e-05,
    "lr_head_decay": 0.00030309278350515467,
    "lr_head_no_decay": 0.00030309278350515467
  },
  {
    "epoch": 52,
    "global_step": 10400,
    "train_loss": 0.17348103545606136,
    "train_miou": 0.8796293139457703,
    "val_loss": 0.589865632538725,
    "val_miou": 0.722500741481781,
    "lr": 2.969072164948454e-05,
    "lr_dict": {
      "encoder_decay": 2.969072164948454e-05,
      "encoder_no_decay": 2.969072164948454e-05,
      "head_decay": 0.0002969072164948454,
      "head_no_decay": 0.0002969072164948454
    },
    "best_miou": 0.7280662059783936,
    "is_best": false,
    "early_bad_epochs": 2,
    "lr_encoder_decay": 2.969072164948454e-05,
    "lr_encoder_no_decay": 2.969072164948454e-05,
    "lr_head_decay": 0.0002969072164948454,
    "lr_head_no_decay": 0.0002969072164948454
  },
  {
    "epoch": 53,
    "global_step": 10600,
    "train_loss": 0.16970487389713526,
    "train_miou": 0.8817687034606934,
    "val_loss": 0.5871975098924683,
    "val_miou": 0.7271932363510132,
    "lr": 2.9072164948453614e-05,
    "lr_dict": {
      "encoder_decay": 2.9072164948453614e-05,
      "encoder_no_decay": 2.9072164948453614e-05,
      "head_decay": 0.00029072164948453616,
      "head_no_decay": 0.00029072164948453616
    },
    "best_miou": 0.7280662059783936,
    "is_best": false,
    "early_bad_epochs": 3,
    "lr_encoder_decay": 2.9072164948453614e-05,
    "lr_encoder_no_decay": 2.9072164948453614e-05,
    "lr_head_decay": 0.00029072164948453616,
    "lr_head_no_decay": 0.00029072164948453616
  },
  {
    "epoch": 54,
    "global_step": 10800,
    "train_loss": 0.16908720783889294,
    "train_miou": 0.8823944926261902,
    "val_loss": 0.5828203893647406,
    "val_miou": 0.7312833666801453,
    "lr": 2.845360824742268e-05,
    "lr_dict": {
      "encoder_decay": 2.845360824742268e-05,
      "encoder_no_decay": 2.845360824742268e-05,
      "head_decay": 0.00028453608247422683,
      "head_no_decay": 0.00028453608247422683
    },
    "best_miou": 0.7312833666801453,
    "is_best": true,
    "early_bad_epochs": 0,
    "lr_encoder_decay": 2.845360824742268e-05,
    "lr_encoder_no_decay": 2.845360824742268e-05,
    "lr_head_decay": 0.00028453608247422683,
    "lr_head_no_decay": 0.00028453608247422683
  },
  {
    "epoch": 55,
    "global_step": 11000,
    "train_loss": 0.17019424218684434,
    "train_miou": 0.8827052116394043,
    "val_loss": 0.5819817972300675,
    "val_miou": 0.724936306476593,
    "lr": 2.7835051546391755e-05,
    "lr_dict": {
      "encoder_decay": 2.7835051546391755e-05,
      "encoder_no_decay": 2.7835051546391755e-05,
      "head_decay": 0.00027835051546391755,
      "head_no_decay": 0.00027835051546391755
    },
    "best_miou": 0.7312833666801453,
    "is_best": false,
    "early_bad_epochs": 1,
    "lr_encoder_decay": 2.7835051546391755e-05,
    "lr_encoder_no_decay": 2.7835051546391755e-05,
    "lr_head_decay": 0.00027835051546391755,
    "lr_head_no_decay": 0.00027835051546391755
  },
  {
    "epoch": 56,
    "global_step": 11200,
    "train_loss": 0.1691696248203516,
    "train_miou": 0.882427990436554,
    "val_loss": 0.5974198341956867,
    "val_miou": 0.7272343635559082,
    "lr": 2.721649484536083e-05,
    "lr_dict": {
      "encoder_decay": 2.721649484536083e-05,
      "encoder_no_decay": 2.721649484536083e-05,
      "head_decay": 0.0002721649484536083,
      "head_no_decay": 0.0002721649484536083
    },
    "best_miou": 0.7312833666801453,
    "is_best": false,
    "early_bad_epochs": 2,
    "lr_encoder_decay": 2.721649484536083e-05,
    "lr_encoder_no_decay": 2.721649484536083e-05,
    "lr_head_decay": 0.0002721649484536083,
    "lr_head_no_decay": 0.0002721649484536083
  },
  {
    "epoch": 57,
    "global_step": 11400,
    "train_loss": 0.16685002949088812,
    "train_miou": 0.8837051391601562,
    "val_loss": 0.6076085727496687,
    "val_miou": 0.727221667766571,
    "lr": 2.6597938144329897e-05,
    "lr_dict": {
      "encoder_decay": 2.6597938144329897e-05,
      "encoder_no_decay": 2.6597938144329897e-05,
      "head_decay": 0.000265979381443299,
      "head_no_decay": 0.000265979381443299
    },
    "best_miou": 0.7312833666801453,
    "is_best": false,
    "early_bad_epochs": 3,
    "lr_encoder_decay": 2.6597938144329897e-05,
    "lr_encoder_no_decay": 2.6597938144329897e-05,
    "lr_head_decay": 0.000265979381443299,
    "lr_head_no_decay": 0.000265979381443299
  },
  {
    "epoch": 58,
    "global_step": 11600,
    "train_loss": 0.1672614584863186,
    "train_miou": 0.8839979767799377,
    "val_loss": 0.594666836443793,
    "val_miou": 0.7281088829040527,
    "lr": 2.597938144329897e-05,
    "lr_dict": {
      "encoder_decay": 2.597938144329897e-05,
      "encoder_no_decay": 2.597938144329897e-05,
      "head_decay": 0.0002597938144329897,
      "head_no_decay": 0.0002597938144329897
    },
    "best_miou": 0.7312833666801453,
    "is_best": false,
    "early_bad_epochs": 4,
    "lr_encoder_decay": 2.597938144329897e-05,
    "lr_encoder_no_decay": 2.597938144329897e-05,
    "lr_head_decay": 0.0002597938144329897,
    "lr_head_no_decay": 0.0002597938144329897
  },
  {
    "epoch": 59,
    "global_step": 11800,
    "train_loss": 0.1638610839098692,
    "train_miou": 0.8853746652603149,
    "val_loss": 0.603452259390225,
    "val_miou": 0.7285745739936829,
    "lr": 2.5360824742268045e-05,
    "lr_dict": {
      "encoder_decay": 2.5360824742268045e-05,
      "encoder_no_decay": 2.5360824742268045e-05,
      "head_decay": 0.0002536082474226805,
      "head_no_decay": 0.0002536082474226805
    },
    "best_miou": 0.7312833666801453,
    "is_best": false,
    "early_bad_epochs": 5,
    "lr_encoder_decay": 2.5360824742268045e-05,
    "lr_encoder_no_decay": 2.5360824742268045e-05,
    "lr_head_decay": 0.0002536082474226805,
    "lr_head_no_decay": 0.0002536082474226805
  },
  {
    "epoch": 60,
    "global_step": 12000,
    "train_loss": 0.16386742882430552,
    "train_miou": 0.8863540291786194,
    "val_loss": 0.6021309803272116,
    "val_miou": 0.7245903015136719,
    "lr": 2.4742268041237112e-05,
    "lr_dict": {
      "encoder_decay": 2.4742268041237112e-05,
      "encoder_no_decay": 2.4742268041237112e-05,
      "head_decay": 0.00024742268041237116,
      "head_no_decay": 0.00024742268041237116
    },
    "best_miou": 0.7312833666801453,
    "is_best": false,
    "early_bad_epochs": 6,
    "lr_encoder_decay": 2.4742268041237112e-05,
    "lr_encoder_no_decay": 2.4742268041237112e-05,
    "lr_head_decay": 0.00024742268041237116,
    "lr_head_no_decay": 0.00024742268041237116
  },
  {
    "epoch": 61,
    "global_step": 12200,
    "train_loss": 0.16260987900197507,
    "train_miou": 0.8856056332588196,
    "val_loss": 0.6032827531762899,
    "val_miou": 0.7224459648132324,
    "lr": 2.4123711340206186e-05,
    "lr_dict": {
      "encoder_decay": 2.4123711340206186e-05,
      "encoder_no_decay": 2.4123711340206186e-05,
      "head_decay": 0.00024123711340206188,
      "head_no_decay": 0.00024123711340206188
    },
    "best_miou": 0.7312833666801453,
    "is_best": false,
    "early_bad_epochs": 7,
    "lr_encoder_decay": 2.4123711340206186e-05,
    "lr_encoder_no_decay": 2.4123711340206186e-05,
    "lr_head_decay": 0.00024123711340206188,
    "lr_head_no_decay": 0.00024123711340206188
  },
  {
    "epoch": 62,
    "global_step": 12400,
    "train_loss": 0.16307113125920294,
    "train_miou": 0.8870149850845337,
    "val_loss": 0.6013664650212368,
    "val_miou": 0.7248680591583252,
    "lr": 2.350515463917526e-05,
    "lr_dict": {
      "encoder_decay": 2.350515463917526e-05,
      "encoder_no_decay": 2.350515463917526e-05,
      "head_decay": 0.00023505154639175263,
      "head_no_decay": 0.00023505154639175263
    },
    "best_miou": 0.7312833666801453,
    "is_best": false,
    "early_bad_epochs": 8,
    "lr_encoder_decay": 2.350515463917526e-05,
    "lr_encoder_no_decay": 2.350515463917526e-05,
    "lr_head_decay": 0.00023505154639175263,
    "lr_head_no_decay": 0.00023505154639175263
  },
  {
    "epoch": 63,
    "global_step": 12600,
    "train_loss": 0.16012675408273935,
    "train_miou": 0.8861710429191589,
    "val_loss": 0.6088106234379003,
    "val_miou": 0.7275682687759399,
    "lr": 2.2886597938144328e-05,
    "lr_dict": {
      "encoder_decay": 2.2886597938144328e-05,
      "encoder_no_decay": 2.2886597938144328e-05,
      "head_decay": 0.0002288659793814433,
      "head_no_decay": 0.0002288659793814433
    },
    "best_miou": 0.7312833666801453,
    "is_best": false,
    "early_bad_epochs": 9,
    "lr_encoder_decay": 2.2886597938144328e-05,
    "lr_encoder_no_decay": 2.2886597938144328e-05,
    "lr_head_decay": 0.0002288659793814433,
    "lr_head_no_decay": 0.0002288659793814433
  },
  {
    "epoch": 64,
    "global_step": 12800,
    "train_loss": 0.16024296190589665,
    "train_miou": 0.8874934315681458,
    "val_loss": 0.6103121354955757,
    "val_miou": 0.7263457775115967,
    "lr": 2.2268041237113402e-05,
    "lr_dict": {
      "encoder_decay": 2.2268041237113402e-05,
      "encoder_no_decay": 2.2268041237113402e-05,
      "head_decay": 0.00022268041237113404,
      "head_no_decay": 0.00022268041237113404
    },
    "best_miou": 0.7312833666801453,
    "is_best": false,
    "early_bad_epochs": 10,
    "lr_encoder_decay": 2.2268041237113402e-05,
    "lr_encoder_no_decay": 2.2268041237113402e-05,
    "lr_head_decay": 0.00022268041237113404,
    "lr_head_no_decay": 0.00022268041237113404
  },
  {
    "epoch": 65,
    "global_step": 13000,
    "train_loss": 0.15801906276494265,
    "train_miou": 0.8881643414497375,
    "val_loss": 0.6063993979851013,
    "val_miou": 0.7270487546920776,
    "lr": 2.1649484536082476e-05,
    "lr_dict": {
      "encoder_decay": 2.1649484536082476e-05,
      "encoder_no_decay": 2.1649484536082476e-05,
      "head_decay": 0.0002164948453608248,
      "head_no_decay": 0.0002164948453608248
    },
    "best_miou": 0.7312833666801453,
    "is_best": false,
    "early_bad_epochs": 11,
    "lr_encoder_decay": 2.1649484536082476e-05,
    "lr_encoder_no_decay": 2.1649484536082476e-05,
    "lr_head_decay": 0.0002164948453608248,
    "lr_head_no_decay": 0.0002164948453608248
  },
  {
    "epoch": 66,
    "global_step": 13200,
    "train_loss": 0.15601058792322875,
    "train_miou": 0.8891872763633728,
    "val_loss": 0.6065632379407366,
    "val_miou": 0.7247703671455383,
    "lr": 2.1030927835051547e-05,
    "lr_dict": {
      "encoder_decay": 2.1030927835051547e-05,
      "encoder_no_decay": 2.1030927835051547e-05,
      "head_decay": 0.00021030927835051546,
      "head_no_decay": 0.00021030927835051546
    },
    "best_miou": 0.7312833666801453,
    "is_best": false,
    "early_bad_epochs": 12,
    "lr_encoder_decay": 2.1030927835051547e-05,
    "lr_encoder_no_decay": 2.1030927835051547e-05,
    "lr_head_decay": 0.00021030927835051546,
    "lr_head_no_decay": 0.00021030927835051546
  },
  {
    "epoch": 67,
    "global_step": 13400,
    "train_loss": 0.1594783877581358,
    "train_miou": 0.8890752196311951,
    "val_loss": 0.6050349564975118,
    "val_miou": 0.7268943190574646,
    "lr": 2.041237113402062e-05,
    "lr_dict": {
      "encoder_decay": 2.041237113402062e-05,
      "encoder_no_decay": 2.041237113402062e-05,
      "head_decay": 0.0002041237113402062,
      "head_no_decay": 0.0002041237113402062
    },
    "best_miou": 0.7312833666801453,
    "is_best": false,
    "early_bad_epochs": 13,
    "lr_encoder_decay": 2.041237113402062e-05,
    "lr_encoder_no_decay": 2.041237113402062e-05,
    "lr_head_decay": 0.0002041237113402062,
    "lr_head_no_decay": 0.0002041237113402062
  },
  {
    "epoch": 68,
    "global_step": 13600,
    "train_loss": 0.15732428845018148,
    "train_miou": 0.8892683982849121,
    "val_loss": 0.603636023152638,
    "val_miou": 0.7264024615287781,
    "lr": 1.9793814432989695e-05,
    "lr_dict": {
      "encoder_decay": 1.9793814432989695e-05,
      "encoder_no_decay": 1.9793814432989695e-05,
      "head_decay": 0.00019793814432989695,
      "head_no_decay": 0.00019793814432989695
    },
    "best_miou": 0.7312833666801453,
    "is_best": false,
    "early_bad_epochs": 14,
    "lr_encoder_decay": 1.9793814432989695e-05,
    "lr_encoder_no_decay": 1.9793814432989695e-05,
    "lr_head_decay": 0.00019793814432989695,
    "lr_head_no_decay": 0.00019793814432989695
  },
  {
    "epoch": 69,
    "global_step": 13800,
    "train_loss": 0.15707146398723126,
    "train_miou": 0.890622079372406,
    "val_loss": 0.6124676380838666,
    "val_miou": 0.7253242135047913,
    "lr": 1.9175257731958763e-05,
    "lr_dict": {
      "encoder_decay": 1.9175257731958763e-05,
      "encoder_no_decay": 1.9175257731958763e-05,
      "head_decay": 0.00019175257731958762,
      "head_no_decay": 0.00019175257731958762
    },
    "best_miou": 0.7312833666801453,
    "is_best": false,
    "early_bad_epochs": 15,
    "lr_encoder_decay": 1.9175257731958763e-05,
    "lr_encoder_no_decay": 1.9175257731958763e-05,
    "lr_head_decay": 0.00019175257731958762,
    "lr_head_no_decay": 0.00019175257731958762
  }
]